pyclmuapp/__init__.py
pyclmuapp/__main__.py
pyclmuapp/_cli.py
pyclmuapp/clmu.py
pyclmuapp/container.py
pyclmuapp/era5_forcing.py
pyclmuapp/era_forcing.py
pyclmuapp/getcity.py
pyclmuapp/pts.py
pyclmuapp/usp.py
pyclmuapp/config/__init__.py
pyclmuapp/config/config_man.json
pyclmuapp/config/ini_docker.json
pyclmuapp/config/ini_docker_1.1.json
pyclmuapp/config/ini_docker_in.json
pyclmuapp/config/ini_sing.json
pyclmuapp/config/ini_sing_1.1.json
pyclmuapp/config/scripts.py
pyclmuapp/config/scripts2.py
pyclmuapp/config/cime_config/config_compilers.xml
pyclmuapp/config/cime_config/config_machines.xml
pyclmuapp/scripts/PTS_build.sh
pyclmuapp/scripts/PTS_revise.sh
pyclmuapp/scripts/PTS_script.sh
pyclmuapp/scripts/PTS_submit.sh
pyclmuapp/scripts/pts.sh
pyclmuapp/scripts/usp.sh
pyclmuapp/scripts/usp_1.1.sh
pyclmuapp/scripts/usp_last_version.sh
pyclmuapp/usp/domain.nc
pyclmuapp/usp/surfdata.nc
pyclmuapp/usp/SourceMods/src.clm/SurfaceAlbedoMod.F90
pyclmuapp/usp/SourceMods/src.clm/clm_varpar.F90
pyclmuapp-0.0.2.dist-info/LICENSE
pyclmuapp-0.0.2.dist-info/METADATA
pyclmuapp-0.0.2.dist-info/WHEEL
pyclmuapp-0.0.2.dist-info/entry_points.txt
pyclmuapp-0.0.2.dist-info/top_level.txt
pyclmuapp-0.0.2.dist-info/RECORD
