Metadata-Version: 2.1
Name: pyclmuapp
Version: 0.0.2
Summary: A Python Package for Integration and Execution of Community Land Model Urban (CLMU) in a Containerized Environment
Home-page: https://github.com/envdes/pyclmuapp
Author: Junjie Yu
Author-email: yjj1997@live.cn
License: MIT
Classifier: Development Status :: 2 - Pre-Alpha
Classifier: Intended Audience :: Science/Research
Classifier: License :: OSI Approved :: MIT License
Classifier: Natural Language :: English
Classifier: Operating System :: OS Independent
Classifier: Programming Language :: Python :: 3
Classifier: Topic :: Scientific/Engineering :: Atmospheric Science
License-File: LICENSE
Requires-Dist: numpy
Requires-Dist: pandas
Requires-Dist: xarray
Requires-Dist: haversine
Requires-Dist: netcdf4
Requires-Dist: nc-time-axis
Requires-Dist: cdsapi
